README.md
setup.py
numerize/__init__.py
numerize/numerize.py
numerize/test.py
numerize.egg-info/PKG-INFO
numerize.egg-info/SOURCES.txt
numerize.egg-info/dependency_links.txt
numerize.egg-info/top_level.txt