Metadata-Version: 2.1
Name: numerize
Version: 0.10
Summary: Convert large numbers into readable numbers for humans.
Home-page: https://github.com/davidsa03/numerize
Author: David Sa
Author-email: davidsa03@gmail.com
License: MIT
Platform: UNKNOWN
